{
  "data": [
    {
      "month": "Jan 2023",
      "year": "2023",
      "quarter": "Q1",
      "total_registrations": 19680,
      "ev_share_pct": 15.0,
      "ev_units": 2952,
      "chinese_share_pct": 8.0,
      "chinese_units": 1574,
      "zeekr_units": 0,
      "lynkco_units": 0
    },
    {
      "month": "Feb 2023",
      "year": "2023",
      "quarter": "Q1",
      "total_registrations": 18814,
      "ev_share_pct": 15.6,
      "ev_units": 2935,
      "chinese_share_pct": 8.7,
      "chinese_units": 1637,
      "zeekr_units": 0,
      "lynkco_units": 0
    },
    {
      "month": "Mar 2023",
      "year": "2023",
      "quarter": "Q1",
      "total_registrations": 21332,
      "ev_share_pct": 16.2,
      "ev_units": 3456,
      "chinese_share_pct": 9.4,
      "chinese_units": 2005,
      "zeekr_units": 0,
      "lynkco_units": 0
    },
    {
      "month": "Apr 2023",
      "year": "2023",
      "quarter": "Q2",
      "total_registrations": 22900,
      "ev_share_pct": 16.8,
      "ev_units": 3847,
      "chinese_share_pct": 10.1,
      "chinese_units": 2313,
      "zeekr_units": 0,
      "lynkco_units": 0
    },
    {
      "month": "May 2023",
      "year": "2023",
      "quarter": "Q2",
      "total_registrations": 23994,
      "ev_share_pct": 17.4,
      "ev_units": 4175,
      "chinese_share_pct": 10.8,
      "chinese_units": 2591,
      "zeekr_units": 0,
      "lynkco_units": 0
    },
    {
      "month": "Jun 2023",
      "year": "2023",
      "quarter": "Q2",
      "total_registrations": 25344,
      "ev_share_pct": 17.9,
      "ev_units": 4537,
      "chinese_share_pct": 11.5,
      "chinese_units": 2915,
      "zeekr_units": 0,
      "lynkco_units": 0
    },
    {
      "month": "Jul 2023",
      "year": "2023",
      "quarter": "Q3",
      "total_registrations": 26213,
      "ev_share_pct": 18.5,
      "ev_units": 4849,
      "chinese_share_pct": 12.2,
      "chinese_units": 3198,
      "zeekr_units": 0,
      "lynkco_units": 0
    },
    {
      "month": "Aug 2023",
      "year": "2023",
      "quarter": "Q3",
      "total_registrations": 22367,
      "ev_share_pct": 19.1,
      "ev_units": 4272,
      "chinese_share_pct": 12.8,
      "chinese_units": 2863,
      "zeekr_units": 0,
      "lynkco_units": 0
    },
    {
      "month": "Sep 2023",
      "year": "2023",
      "quarter": "Q3",
      "total_registrations": 27974,
      "ev_share_pct": 19.7,
      "ev_units": 5511,
      "chinese_share_pct": 13.5,
      "chinese_units": 3776,
      "zeekr_units": 0,
      "lynkco_units": 0
    },
    {
      "month": "Oct 2023",
      "year": "2023",
      "quarter": "Q4",
      "total_registrations": 29118,
      "ev_share_pct": 20.3,
      "ev_units": 5911,
      "chinese_share_pct": 14.2,
      "chinese_units": 4135,
      "zeekr_units": 0,
      "lynkco_units": 0
    },
    {
      "month": "Nov 2023",
      "year": "2023",
      "quarter": "Q4",
      "total_registrations": 28759,
      "ev_share_pct": 20.9,
      "ev_units": 6011,
      "chinese_share_pct": 14.9,
      "chinese_units": 4285,
      "zeekr_units": 0,
      "lynkco_units": 0
    },
    {
      "month": "Dec 2023",
      "year": "2023",
      "quarter": "Q4",
      "total_registrations": 30171,
      "ev_share_pct": 21.5,
      "ev_units": 6487,
      "chinese_share_pct": 15.6,
      "chinese_units": 4707,
      "zeekr_units": 0,
      "lynkco_units": 0
    },
    {
      "month": "Jan 2024",
      "year": "2024",
      "quarter": "Q1",
      "total_registrations": 20894,
      "ev_share_pct": 22.1,
      "ev_units": 4618,
      "chinese_share_pct": 16.3,
      "chinese_units": 3406,
      "zeekr_units": 0,
      "lynkco_units": 0
    },
    {
      "month": "Feb 2024",
      "year": "2024",
      "quarter": "Q1",
      "total_registrations": 19974,
      "ev_share_pct": 22.7,
      "ev_units": 4534,
      "chinese_share_pct": 17.0,
      "chinese_units": 3396,
      "zeekr_units": 0,
      "lynkco_units": 0
    },
    {
      "month": "Mar 2024",
      "year": "2024",
      "quarter": "Q1",
      "total_registrations": 22647,
      "ev_share_pct": 23.3,
      "ev_units": 5277,
      "chinese_share_pct": 17.7,
      "chinese_units": 4009,
      "zeekr_units": 0,
      "lynkco_units": 0
    },
    {
      "month": "Apr 2024",
      "year": "2024",
      "quarter": "Q2",
      "total_registrations": 24313,
      "ev_share_pct": 23.8,
      "ev_units": 5786,
      "chinese_share_pct": 18.4,
      "chinese_units": 4474,
      "zeekr_units": 0,
      "lynkco_units": 0
    },
    {
      "month": "May 2024",
      "year": "2024",
      "quarter": "Q2",
      "total_registrations": 25474,
      "ev_share_pct": 24.4,
      "ev_units": 6216,
      "chinese_share_pct": 19.1,
      "chinese_units": 4866,
      "zeekr_units": 0,
      "lynkco_units": 0
    },
    {
      "month": "Jun 2024",
      "year": "2024",
      "quarter": "Q2",
      "total_registrations": 26907,
      "ev_share_pct": 25.0,
      "ev_units": 6727,
      "chinese_share_pct": 19.8,
      "chinese_units": 5328,
      "zeekr_units": 0,
      "lynkco_units": 0
    },
    {
      "month": "Jul 2024",
      "year": "2024",
      "quarter": "Q3",
      "total_registrations": 27830,
      "ev_share_pct": 25.6,
      "ev_units": 7124,
      "chinese_share_pct": 20.5,
      "chinese_units": 5705,
      "zeekr_units": 250,
      "lynkco_units": 0
    },
    {
      "month": "Aug 2024",
      "year": "2024",
      "quarter": "Q3",
      "total_registrations": 23747,
      "ev_share_pct": 26.2,
      "ev_units": 6222,
      "chinese_share_pct": 21.2,
      "chinese_units": 5034,
      "zeekr_units": 272,
      "lynkco_units": 0
    },
    {
      "month": "Sep 2024",
      "year": "2024",
      "quarter": "Q3",
      "total_registrations": 29700,
      "ev_share_pct": 26.8,
      "ev_units": 7960,
      "chinese_share_pct": 21.8,
      "chinese_units": 6475,
      "zeekr_units": 294,
      "lynkco_units": 0
    },
    {
      "month": "Oct 2024",
      "year": "2024",
      "quarter": "Q4",
      "total_registrations": 30914,
      "ev_share_pct": 27.4,
      "ev_units": 8470,
      "chinese_share_pct": 22.5,
      "chinese_units": 6956,
      "zeekr_units": 316,
      "lynkco_units": 0
    },
    {
      "month": "Nov 2024",
      "year": "2024",
      "quarter": "Q4",
      "total_registrations": 30533,
      "ev_share_pct": 28.0,
      "ev_units": 8549,
      "chinese_share_pct": 23.2,
      "chinese_units": 7084,
      "zeekr_units": 338,
      "lynkco_units": 0
    },
    {
      "month": "Dec 2024",
      "year": "2024",
      "quarter": "Q4",
      "total_registrations": 32032,
      "ev_share_pct": 28.6,
      "ev_units": 9161,
      "chinese_share_pct": 23.9,
      "chinese_units": 7656,
      "zeekr_units": 360,
      "lynkco_units": 0
    },
    {
      "month": "Jan 2025",
      "year": "2025",
      "quarter": "Q1",
      "total_registrations": 22183,
      "ev_share_pct": 29.2,
      "ev_units": 6477,
      "chinese_share_pct": 24.6,
      "chinese_units": 5457,
      "zeekr_units": 382,
      "lynkco_units": 0
    },
    {
      "month": "Feb 2025",
      "year": "2025",
      "quarter": "Q1",
      "total_registrations": 21206,
      "ev_share_pct": 29.7,
      "ev_units": 6298,
      "chinese_share_pct": 25.3,
      "chinese_units": 5365,
      "zeekr_units": 404,
      "lynkco_units": 0
    },
    {
      "month": "Mar 2025",
      "year": "2025",
      "quarter": "Q1",
      "total_registrations": 24044,
      "ev_share_pct": 30.3,
      "ev_units": 7285,
      "chinese_share_pct": 26.0,
      "chinese_units": 6251,
      "zeekr_units": 426,
      "lynkco_units": 100
    },
    {
      "month": "Apr 2025",
      "year": "2025",
      "quarter": "Q2",
      "total_registrations": 25812,
      "ev_share_pct": 30.9,
      "ev_units": 7976,
      "chinese_share_pct": 26.7,
      "chinese_units": 6892,
      "zeekr_units": 448,
      "lynkco_units": 112
    },
    {
      "month": "May 2025",
      "year": "2025",
      "quarter": "Q2",
      "total_registrations": 27045,
      "ev_share_pct": 31.5,
      "ev_units": 8519,
      "chinese_share_pct": 27.4,
      "chinese_units": 7410,
      "zeekr_units": 470,
      "lynkco_units": 124
    },
    {
      "month": "Jun 2025",
      "year": "2025",
      "quarter": "Q2",
      "total_registrations": 28567,
      "ev_share_pct": 32.1,
      "ev_units": 9170,
      "chinese_share_pct": 28.1,
      "chinese_units": 8027,
      "zeekr_units": 492,
      "lynkco_units": 136
    },
    {
      "month": "Jul 2025",
      "year": "2025",
      "quarter": "Q3",
      "total_registrations": 29546,
      "ev_share_pct": 32.7,
      "ev_units": 9662,
      "chinese_share_pct": 28.8,
      "chinese_units": 8509,
      "zeekr_units": 514,
      "lynkco_units": 148
    },
    {
      "month": "Aug 2025",
      "year": "2025",
      "quarter": "Q3",
      "total_registrations": 25212,
      "ev_share_pct": 33.3,
      "ev_units": 8396,
      "chinese_share_pct": 29.5,
      "chinese_units": 7438,
      "zeekr_units": 536,
      "lynkco_units": 160
    },
    {
      "month": "Sep 2025",
      "year": "2025",
      "quarter": "Q3",
      "total_registrations": 31531,
      "ev_share_pct": 33.9,
      "ev_units": 10689,
      "chinese_share_pct": 30.2,
      "chinese_units": 9522,
      "zeekr_units": 558,
      "lynkco_units": 172
    },
    {
      "month": "Oct 2025",
      "year": "2025",
      "quarter": "Q4",
      "total_registrations": 32821,
      "ev_share_pct": 34.5,
      "ev_units": 11323,
      "chinese_share_pct": 30.8,
      "chinese_units": 10109,
      "zeekr_units": 580,
      "lynkco_units": 184
    },
    {
      "month": "Nov 2025",
      "year": "2025",
      "quarter": "Q4",
      "total_registrations": 32416,
      "ev_share_pct": 35.1,
      "ev_units": 11378,
      "chinese_share_pct": 31.5,
      "chinese_units": 10211,
      "zeekr_units": 602,
      "lynkco_units": 196
    },
    {
      "month": "Dec 2025",
      "year": "2025",
      "quarter": "Q4",
      "total_registrations": 34007,
      "ev_share_pct": 35.6,
      "ev_units": 12106,
      "chinese_share_pct": 32.2,
      "chinese_units": 10950,
      "zeekr_units": 624,
      "lynkco_units": 208
    },
    {
      "month": "Jan 2026",
      "year": "2026",
      "quarter": "Q1",
      "total_registrations": 23551,
      "ev_share_pct": 36.2,
      "ev_units": 8525,
      "chinese_share_pct": 32.9,
      "chinese_units": 7748,
      "zeekr_units": 646,
      "lynkco_units": 220
    },
    {
      "month": "Feb 2026",
      "year": "2026",
      "quarter": "Q1",
      "total_registrations": 22514,
      "ev_share_pct": 36.8,
      "ev_units": 8285,
      "chinese_share_pct": 33.6,
      "chinese_units": 7565,
      "zeekr_units": 668,
      "lynkco_units": 232
    },
    {
      "month": "Mar 2026",
      "year": "2026",
      "quarter": "Q1",
      "total_registrations": 25527,
      "ev_share_pct": 37.4,
      "ev_units": 9547,
      "chinese_share_pct": 34.3,
      "chinese_units": 8756,
      "zeekr_units": 690,
      "lynkco_units": 244
    },
    {
      "month": "Apr 2026",
      "year": "2026",
      "quarter": "Q2",
      "total_registrations": 27404,
      "ev_share_pct": 38.0,
      "ev_units": 10414,
      "chinese_share_pct": 35.0,
      "chinese_units": 9591,
      "zeekr_units": 700,
      "lynkco_units": 250
    }
  ]
}